meterhub_pretrain/__init__.py
meterhub_pretrain/dataset.py
meterhub_pretrain/learner.py
meterhub_pretrain/main.py
meterhub_pretrain/metric.py
meterhub_pretrain/models.py
meterhub_pretrain/organ/__init__.py
meterhub_pretrain/organ/dataset.py
ppocr/__init__.py
meterhub_pretrain-0.2.0.dist-info/METADATA
meterhub_pretrain-0.2.0.dist-info/WHEEL
meterhub_pretrain-0.2.0.dist-info/top_level.txt
meterhub_pretrain-0.2.0.dist-info/RECORD
