Metadata-Version: 2.1
Name: meterhub-pretrain
Version: 0.2.0
Summary: Default template for PDM package
Author-email: svtter <svtter@qq.com>
License: MIT
Requires-Python: !=3.9.7,~=3.9.0
Requires-Dist: torch
Requires-Dist: torchvision
Requires-Dist: transformers >=4.45.2
Requires-Dist: paddlepaddle-gpu >=2.6.2
Requires-Dist: shapely >=2.0.6
Requires-Dist: shareds >=0.2.0
